README.rst
setup.py
tinyos/__init__.py
tinyos/tos.py
tinyos.egg-info/PKG-INFO
tinyos.egg-info/SOURCES.txt
tinyos.egg-info/dependency_links.txt
tinyos.egg-info/requires.txt
tinyos.egg-info/top_level.txt
tinyos/message/Message.py
tinyos/message/MoteIF.py
tinyos/message/__init__.py
tinyos/misc/__init__.py
tinyos/misc/hexdump.py
tinyos/packet/IO.py
tinyos/packet/PacketDispatcher.py
tinyos/packet/PacketSource.py
tinyos/packet/Platform.py
tinyos/packet/SFProtocol.py
tinyos/packet/SFSource.py
tinyos/packet/SerialIO.py
tinyos/packet/SerialProtocol.py
tinyos/packet/SerialSource.py
tinyos/packet/SocketIO.py
tinyos/packet/ThreadTask.py
tinyos/packet/__init__.py
tinyos/packet/avrmote.py
tinyos/tossim/TossimApp.py
tinyos/tossim/TossimNescDecls.py
tinyos/tossim/__init__.py
tinyos/utils/Singleton.py
tinyos/utils/Watcher.py
tinyos/utils/__init__.py