Metadata-Version: 1.1
Name: tinyos
Version: 2.1.2.2
Summary: Highly experimental TinyOS python tools (Unofficial Packaging)
Home-page: UNKNOWN
Author: UNKNOWN
Author-email: UNKNOWN
License: UNKNOWN
Platform: UNKNOWN
Classifier: Intended Audience :: Developers
Classifier: Programming Language :: Python :: 2.7
Classifier: Topic :: Software Development :: Libraries :: Python Modules
